setup.py
respite/__init__.py
respite/decorators.py
respite/formats.py
respite/inflector.py
respite/middleware.py
respite/settings.py
respite/utils.py
respite.egg-info/PKG-INFO
respite.egg-info/SOURCES.txt
respite.egg-info/dependency_links.txt
respite.egg-info/top_level.txt
respite/lib/__init__.py
respite/lib/ordereddict.py
respite/serializers/__init__.py
respite/serializers/base.py
respite/serializers/jsonserializer.py
respite/serializers/xmlserializer.py
respite/urls/__init__.py
respite/urls/routes.py
respite/views/__init__.py
respite/views/resource.py
respite/views/views.py