Metadata-Version: 1.0
Name: respite
Version: 1.0.0
Summary: Respite conforms Django to Representational State Transfer (REST)
Home-page: http://github.com/jgorset/respite
Author: Johannes Gorset
Author-email: jgorset@gmail.com
License: UNKNOWN
Platform: UNKNOWN
